geigerlog/__init__.py
geigerlog/__main__.py
geigerlog/ei1050.py
geigerlog/gdev_ambiomon.py
geigerlog/gdev_audio.py
geigerlog/gdev_gmc.py
geigerlog/gdev_gmc_hist.py
geigerlog/gdev_i2c.py
geigerlog/gdev_i2c_Dngl_ELV.py
geigerlog/gdev_i2c_Sensor_BME280.py
geigerlog/gdev_i2c_Sensor_TSL2591.py
geigerlog/gdev_labjack.py
geigerlog/gdev_minimon.py
geigerlog/gdev_radmon.py
geigerlog/gdev_raspi.py
geigerlog/gdev_scout.py
geigerlog/gdev_simul.py
geigerlog/geigerlog.py
geigerlog/ggeiger.py
geigerlog/gglobs.py
geigerlog/gstat_convfft.py
geigerlog/gstat_fft.py
geigerlog/gstat_poisson.py
geigerlog/gstat_synth.py
geigerlog/gsup_plot.py
geigerlog/gsup_sql.py
geigerlog/gsup_tools.py
geigerlog/gsup_utils.py
tests/GLsermon.py
tests/__init__.py
geigerlog-0.0.13.dist-info/LICENSE
geigerlog-0.0.13.dist-info/METADATA
geigerlog-0.0.13.dist-info/WHEEL
geigerlog-0.0.13.dist-info/top_level.txt
geigerlog-0.0.13.dist-info/RECORD
