Metadata-Version: 2.1
Name: geigerlog
Version: 0.0.13
Summary: Preparations for GeigerLog
Home-page: https://sourceforge.net/projects/geigerlog/
Author: ullix
Author-email: ullixgl@gmail.com
License: UNKNOWN
Project-URL: Bug Tracker, https://sourceforge.net/p/geigerlog/discussion/
Project-URL: Articles, https://sourceforge.net/projects/geigerlog/files/Articles/
Project-URL: Data files, https://sourceforge.net/projects/geigerlog/files/Data - synthetic - as log files/
Project-URL: Testing, https://sourceforge.net/projects/geigerlog/files/testing/
Platform: UNKNOWN
Classifier: Programming Language :: Python :: 3
Classifier: License :: OSI Approved :: GNU General Public License v3 (GPLv3)
Classifier: Operating System :: OS Independent
Classifier: Topic :: Scientific/Engineering :: Physics
Classifier: Topic :: Scientific/Engineering :: Visualization
Requires-Python: >=3.6
Requires-Dist: numpy (>=1.20.1)
Requires-Dist: scipy (>=1.6.1)
Requires-Dist: matplotlib (>=3.3.4)
Requires-Dist: PyQt5
Requires-Dist: sounddevice
Requires-Dist: soundfile
Requires-Dist: pyserial
